{
  "layout": "password",
  "sections": {
    "main": {
      "type": "password-template",
      "settings": {
        "bg_color": "bg-neutral",
        "bg_color_shade": 500,
        "image": "shopify:\/\/shop_images\/Perfocal_27-02-21_NYXG4FJF_36_48ccb55d-1b36-4658-a621-d5658de81b94.jpg",
        "image_mob": "shopify:\/\/shop_images\/Perfocal_27-02-21_NYXG4FJF_36_48ccb55d-1b36-4658-a621-d5658de81b94.jpg",
        "logo_pos": "logo_center",
        "text-align": "text-center justify-center",
        "title": "WE’RE TAKING A LITTLE BREAK TO FRESHEN UP. WE’LL BE BACK SOON!",
        "title_typeface": "font-headline",
        "title_size": "text-headline-2 lg:text-headline-2-lg",
        "title_weight": "font-semibold",
        "title_color": "text-neutral",
        "title_color_shade": 900,
        "subtitle_newsletter": "<p>In the meantime, why not sign up to our newsletter to keep up to date?<\/p>",
        "subtitle_form": "<p>Enter store password<\/p>",
        "subtitle_typeface": "font-body",
        "subtitle_size": "text-body-large lg:text-body-large-lg",
        "subtitle_weight": "font-light",
        "subtitle_color": "text-neutral",
        "subtitle_color_shade": 900,
        "show_password": "Are you the site owner?",
        "show_form": "Go back to newsletter sign up"
      }
    }
  },
  "order": [
    "main"
  ]
}